infrastructure_diagram_mcp_server/__init__.py
infrastructure_diagram_mcp_server/diagrams_tools.py
infrastructure_diagram_mcp_server/models.py
infrastructure_diagram_mcp_server/scanner.py
infrastructure_diagram_mcp_server/server.py
infrastructure_diagram_mcp_server/parsers/__init__.py
infrastructure_diagram_mcp_server/parsers/helm_parser.py
infrastructure_diagram_mcp_server/parsers/icon_resolver.py
infrastructure_diagram_mcp_server/parsers/k8s_parser.py
infrastructure_diagram_mcp_server/parsers/terraform_parser.py
infrastructure_diagram_mcp_server-0.0.4.3.dist-info/METADATA
infrastructure_diagram_mcp_server-0.0.4.3.dist-info/WHEEL
infrastructure_diagram_mcp_server-0.0.4.3.dist-info/entry_points.txt
infrastructure_diagram_mcp_server-0.0.4.3.dist-info/licenses/LICENSE
infrastructure_diagram_mcp_server-0.0.4.3.dist-info/licenses/NOTICE
infrastructure_diagram_mcp_server-0.0.4.3.dist-info/RECORD
