Metadata-Version: 2.4
Name: infrastructure-diagram-mcp-server
Version: 0.0.4.3
Summary: An MCP server that seamlessly creates infrastructure diagrams for any cloud provider using the Python diagrams package DSL
Project-URL: Source, https://github.com/andrewmoshu/diagram-mcp-server
Author: Infrastructure Diagram MCP
License: Apache-2.0
License-File: LICENSE
License-File: NOTICE
Classifier: License :: OSI Approved :: Apache Software License
Classifier: Operating System :: OS Independent
Classifier: Programming Language :: Python
Classifier: Programming Language :: Python :: 3
Classifier: Programming Language :: Python :: 3.12
Classifier: Programming Language :: Python :: 3.13
Requires-Python: >=3.12
Requires-Dist: bandit>=1.8.6
Requires-Dist: boto3>=1.40.53
Requires-Dist: diagrams>=0.24.4
Requires-Dist: graphviz2drawio>=1.1.0
Requires-Dist: mcp[cli]>=1.23.0
Requires-Dist: pydantic>=2.12.2
Requires-Dist: python-hcl2>=4.3.0
Requires-Dist: pyyaml>=6.0.1
Requires-Dist: sarif-om>=1.0.4
Requires-Dist: setuptools>=80.9.0
Requires-Dist: starlette>=0.48.0
Requires-Dist: urllib3>=2.5.0
